BASNET/Basnet.py
BASNET/RefUnet.py
BASNET/ResidualBlock.py
BASNET/Resnet34Layers.py
BASNET/__init__.py
BASNET/loss.py
SODBASNET-0.0.5.dist-info/LICENSE
SODBASNET-0.0.5.dist-info/METADATA
SODBASNET-0.0.5.dist-info/WHEEL
SODBASNET-0.0.5.dist-info/top_level.txt
SODBASNET-0.0.5.dist-info/RECORD
