Metadata-Version: 2.1
Name: SODBASNET
Version: 0.0.5
Summary: BASNET model created using tensorflow.
Home-page: https://github.com/Shivam-21-11/Basnet-Model_Package
Author: Shivam Singh
Author-email: Shivamsingh2111@gmail.com
License: MIT
Keywords: Machine Learning
Classifier: Development Status :: 5 - Production/Stable
Classifier: License :: OSI Approved :: MIT License
Classifier: Programming Language :: Python :: 3.10
Classifier: Operating System :: OS Independent
License-File: LICENSE
Requires-Dist: tensorflow
Requires-Dist: numpy
Requires-Dist: keras
